LICENSE
MANIFEST.in
README.md
setup.py
drfbro/__init__.py
drfbro/serializers.py
drfbro/urls.py
drfbro/views.py
drfbro.egg-info/PKG-INFO
drfbro.egg-info/SOURCES.txt
drfbro.egg-info/dependency_links.txt
drfbro.egg-info/not-zip-safe
drfbro.egg-info/requires.txt
drfbro.egg-info/top_level.txt
drfbro/static/drfbro/Gulpfile.js
drfbro/static/drfbro/package.json
drfbro/static/drfbro/gen/app.js
drfbro/static/drfbro/gen/bundle.js
drfbro/static/drfbro/src/app.jsx
drfbro/templates/drfbro/index.html