Metadata-Version: 1.1
Name: drfbro
Version: 0.0.2
Summary: drfbro - a better Django REST Framework browser.
Home-page: https://github.com/and3rson/drfbro
Author: Andrew Dunai
Author-email: andrew@dun.ai
License: MIT
Keywords: django,rest,framework,drf,restframework,browser,navigator
Platform: UNKNOWN
Classifier: Development Status :: 5 - Production/Stable
Classifier: Environment :: Web Environment
Classifier: Framework :: Django
Classifier: Intended Audience :: Developers
Classifier: License :: OSI Approved :: MIT License
Classifier: Operating System :: OS Independent
Classifier: Programming Language :: Python
